datus/__init__.py
datus/main.py
datus/multi_round_benchmark.py
datus/agent/__init__.py
datus/agent/agent.py
datus/agent/evaluate.py
datus/agent/plan.py
datus/agent/reflect.py
datus/agent/workflow.py
datus/agent/workflow.yml
datus/agent/workflow_runner.py
datus/agent/node/__init__.py
datus/agent/node/agentic_node.py
datus/agent/node/begin_node.py
datus/agent/node/chat_agentic_node.py
datus/agent/node/compare_agentic_node.py
datus/agent/node/compare_node.py
datus/agent/node/date_parser_node.py
datus/agent/node/doc_search_node.py
datus/agent/node/execute_sql_node.py
datus/agent/node/fix_node.py
datus/agent/node/gen_ext_knowledge_agentic_node.py
datus/agent/node/gen_metrics_agentic_node.py
datus/agent/node/gen_report_agentic_node.py
datus/agent/node/gen_semantic_model_agentic_node.py
datus/agent/node/gen_sql_agentic_node.py
datus/agent/node/generate_sql_node.py
datus/agent/node/hitl_node.py
datus/agent/node/node.py
datus/agent/node/output_node.py
datus/agent/node/parallel_node.py
datus/agent/node/reason_sql_node.py
datus/agent/node/reflect_node.py
datus/agent/node/schema_linking_node.py
datus/agent/node/search_metrics_node.py
datus/agent/node/selection_node.py
datus/agent/node/sql_summary_agentic_node.py
datus/agent/node/subworkflow_node.py
datus/api/README.md
datus/api/__init__.py
datus/api/auth.py
datus/api/models.py
datus/api/server.py
datus/api/service.py
datus/cli/README.md
datus/cli/__init__.py
datus/cli/_cli_utils.py
datus/cli/action_history_display.py
datus/cli/agent_commands.py
datus/cli/autocomplete.py
datus/cli/bi_dashboard.py
datus/cli/blocking_input_manager.py
datus/cli/chat_commands.py
datus/cli/cli_context.py
datus/cli/context_commands.py
datus/cli/execution_state.py
datus/cli/generation_hooks.py
datus/cli/init_util.py
datus/cli/interactive_init.py
datus/cli/main.py
datus/cli/mcp_commands.py
datus/cli/metadata_commands.py
datus/cli/namespace_manager.py
datus/cli/plan_hooks.py
datus/cli/repl.py
datus/cli/sub_agent_commands.py
datus/cli/sub_agent_wizard.py
datus_agent-0.2.4.dist-info/licenses/LICENSE
datus_agent-0.2.4.dist-info/METADATA
datus_agent-0.2.4.dist-info/WHEEL
datus_agent-0.2.4.dist-info/entry_points.txt
datus_agent-0.2.4.dist-info/top_level.txt
datus_agent-0.2.4.dist-info/RECORD
