Metadata-Version: 2.4
Name: datus-agent
Version: 0.2.4
Summary: AI-powered SQL Agent for data engineering (Compiled Version)
Author-email: Datus Team <harrison.zhao@datus.ai>
Maintainer-email: Datus Team <harrison.zhao@datus.ai>
License-Expression: Apache-2.0
Project-URL: Homepage, https://datus.ai/
Project-URL: Documentation, https://github.com/datus-ai/datus-agent#readme
Project-URL: Repository, https://github.com/datus-ai/datus-agent
Project-URL: Bug Tracker, https://github.com/datus-ai/datus-agent/issues
Keywords: sql,ai,agent,database,nlp,natural-language
Classifier: Development Status :: 3 - Alpha
Classifier: Intended Audience :: Developers
Classifier: Topic :: Database
Classifier: Topic :: Software Development :: Libraries :: Python Modules
Classifier: Programming Language :: Python :: 3
Classifier: Programming Language :: Python :: 3.12
Requires-Python: >=3.12
License-File: LICENSE
Requires-Dist: python-dotenv==1.0.0
Requires-Dist: pandas==2.1.4
Requires-Dist: sqlalchemy==2.0.23
Requires-Dist: sqlglot>=26.12.0
Requires-Dist: pyyaml==6.0.1
Requires-Dist: structlog>=23.1.0
Requires-Dist: openai>=1.95.0
Requires-Dist: httpx[socks]==0.27.2
Requires-Dist: tantivy>=0.22.2
Requires-Dist: aiohttp>=3.11.16
Requires-Dist: xlsxwriter>=3.2.2
Requires-Dist: tiktoken>=0.9.0
Requires-Dist: openai-agents==0.3.2
Requires-Dist: pydantic<3.0,>=2.11.7
Requires-Dist: lancedb==0.18.0
Requires-Dist: pyarrow<19.0.0
Requires-Dist: rich==14.0.0
Requires-Dist: prompt_toolkit>=3.0.51
Requires-Dist: pygments>=2.18.0
Requires-Dist: textual[syntax]==5.1.1
Requires-Dist: anthropic==0.51.0
Requires-Dist: duckdb-engine>=0.17.0
Requires-Dist: duckdb==1.3.0
Requires-Dist: mcp>=1.11.0
Requires-Dist: anyio>=4.9.0
Requires-Dist: json-repair>=0.47.6
Requires-Dist: fastapi<1.0,>=0.104.0
Requires-Dist: uvicorn>=0.24.0
Requires-Dist: google-generativeai>=0.8.0
Requires-Dist: pyperclip==1.9.0
Requires-Dist: streamlit>=1.38.0
Requires-Dist: wcmatch>=10.0
Requires-Dist: fastembed==0.4.2
Requires-Dist: uv>=0.9.9
Requires-Dist: plotly>=6.5.0
Requires-Dist: charset-normalizer>=3.4.2
Dynamic: license-file
